biocrnpyler/__init__.py
biocrnpyler/_version.py
biocrnpyler/components/__init__.py
biocrnpyler/components/basic.py
biocrnpyler/components/combinatorial_complex.py
biocrnpyler/components/combinatorial_conformation.py
biocrnpyler/components/component_enumerator.py
biocrnpyler/components/construct_explorer.py
biocrnpyler/components/integrase_enumerator.py
biocrnpyler/components/membrane.py
biocrnpyler/components/dna/__init__.py
biocrnpyler/components/dna/assembly.py
biocrnpyler/components/dna/cds.py
biocrnpyler/components/dna/construct.py
biocrnpyler/components/dna/misc.py
biocrnpyler/components/dna/promoter.py
biocrnpyler/components/dna/rbs.py
biocrnpyler/components/dna/terminator.py
biocrnpyler/core/__init__.py
biocrnpyler/core/chemical_reaction_network.py
biocrnpyler/core/compartment.py
biocrnpyler/core/component.py
biocrnpyler/core/mechanism.py
biocrnpyler/core/mixture.py
biocrnpyler/core/parameter.py
biocrnpyler/core/polymer.py
biocrnpyler/core/propensities.py
biocrnpyler/core/reaction.py
biocrnpyler/core/species.py
biocrnpyler/mechanisms/__init__.py
biocrnpyler/mechanisms/binding.py
biocrnpyler/mechanisms/conformation.py
biocrnpyler/mechanisms/enzyme.py
biocrnpyler/mechanisms/global_mechanisms.py
biocrnpyler/mechanisms/integrase.py
biocrnpyler/mechanisms/metabolite.py
biocrnpyler/mechanisms/signaling.py
biocrnpyler/mechanisms/transport.py
biocrnpyler/mechanisms/txtl.py
biocrnpyler/mixtures/__init__.py
biocrnpyler/mixtures/cell.py
biocrnpyler/mixtures/extract.py
biocrnpyler/utils/__init__.py
biocrnpyler/utils/general.py
biocrnpyler/utils/plotting.py
biocrnpyler/utils/sbmlutil.py
biocrnpyler/utils/units.py
biocrnpyler-1.3.2.dist-info/licenses/LICENSE
biocrnpyler-1.3.2.dist-info/METADATA
biocrnpyler-1.3.2.dist-info/WHEEL
biocrnpyler-1.3.2.dist-info/top_level.txt
biocrnpyler-1.3.2.dist-info/RECORD
