Metadata-Version: 2.4
Name: BioCRNpyler
Version: 1.3.2
Summary: A chemical reaction network compiler for generating large biological circuit models
Author: Build-A-Cell
License: BSD 3-Clause License
Project-URL: Homepage, https://github.com/buildacell/biocrnpyler/
Project-URL: Bug Tracker, https://github.com/buildacell/biocrnpyler/issues
Keywords: SBML,synthetic biology,modeling,Chemical Reaction Network,CRN
Classifier: Development Status :: 5 - Production/Stable
Classifier: Intended Audience :: Science/Research
Classifier: License :: OSI Approved :: BSD License
Classifier: Programming Language :: Python
Classifier: Programming Language :: Python :: 3
Classifier: Programming Language :: Python :: 3.8
Classifier: Programming Language :: Python :: 3.9
Classifier: Programming Language :: Python :: 3.10
Classifier: Programming Language :: Python :: 3.11
Classifier: Programming Language :: Python :: 3.12
Classifier: Topic :: Software Development
Classifier: Topic :: Scientific/Engineering
Classifier: Operating System :: OS Independent
Requires-Python: >=3.9
License-File: LICENSE
Requires-Dist: python-libsbml
Requires-Dist: numpy<2.0
Requires-Dist: matplotlib
Requires-Dist: networkx
Requires-Dist: bokeh>=1.4.0
Requires-Dist: fa2_modified
Requires-Dist: jupyter
Requires-Dist: pytest
Requires-Dist: pytest-cov
Requires-Dist: nbconvert
Provides-Extra: test
Requires-Dist: pytest; extra == "test"
Dynamic: license-file
